<suitelet scriptid="customscript_idev_sl_sf_script_core">
  <description>The core script of the NetSuite SuiteFrame Scripts project.</description>
  <isinactive>F</isinactive>
  <name>SuiteFrameScript Core </name>
  <notifyadmins>F</notifyadmins>
  <notifyemails></notifyemails>
  <notifyowner>T</notifyowner>
  <notifyuser>F</notifyuser>
  <scriptfile>[/SuiteScripts/SuiteFrameScript/suiteframe.core.suitelet.js]</scriptfile>
  <scriptdeployments>
    <scriptdeployment scriptid="customdeploy_idev_sl_sf_script_core">
      <allemployees>F</allemployees>
      <allpartners>F</allpartners>
      <allroles>T</allroles>
      <audemployee></audemployee>
      <audslctrole></audslctrole>
      <eventtype></eventtype>
      <isdeployed>T</isdeployed>
      <isonline>F</isonline>
      <loglevel>DEBUG</loglevel>
      <runasrole></runasrole>
      <status>RELEASED</status>
      <title>SuiteFrameScript Core</title>
    </scriptdeployment>
  </scriptdeployments>
</suitelet>